[{
    "class2Id": "28",
    "id": "87",
    "name": "米面",
    "parent_id": "28",
    "order_id": "100.00",
    "is_show": "1",
    "step": "3",
    "cat_path": "16,28",
    "ename": "",
    "photo": "https:\/\/imgjd7.fruitday.com\/",
    "product_id": null,
    "class_photo": "https:\/\/imgjd7.fruitday.com\/images\/2017-02-22\/00bf10cf4aa929117e2f4d623fb818b0.png",
    "send_region": null,
    "link": null,
    "is_split": "0",
    "is_hot": "0",
    "is_scene": "0",
    "banner_id": "0"
}, {
    "class2Id": "28",
    "id": "86",
    "name": "食用油",
    "parent_id": "28",
    "order_id": "90.00",
    "is_show": "1",
    "step": "3",
    "cat_path": "16,28",
    "ename": "",
    "photo": "https:\/\/imgjd6.fruitday.com\/",
    "product_id": null,
    "class_photo": "https:\/\/imgjd6.fruitday.com\/images\/2017-02-22\/2b4e642f0c0e245ec72401e784d942f8.png",
    "send_region": null,
    "link": null,
    "is_split": "0",
    "is_hot": "0",
    "is_scene": "0",
    "banner_id": "0"
}, {
    "class2Id": "28",
    "id": "90",
    "name": "烹调汁",
    "parent_id": "28",
    "order_id": "5.00",
    "is_show": "1",
    "step": "3",
    "cat_path": "16,28",
    "ename": "",
    "photo": "https:\/\/imgjd1.fruitday.com\/",
    "product_id": null,
    "class_photo": "https:\/\/imgjd1.fruitday.com\/images\/2017-02-22\/67b4a780b95a88b4ede2d51c97bacd24.png",
    "send_region": null,
    "link": null,
    "is_split": "0",
    "is_hot": "0",
    "is_scene": "0",
    "banner_id": "0"
}, {
    "class2Id": "28",
    "id": "88",
    "name": "南北干货",
    "parent_id": "28",
    "order_id": "3.00",
    "is_show": "1",
    "step": "3",
    "cat_path": "16,28",
    "ename": "",
    "photo": "https:\/\/imgqn8.fruitday.com\/",
    "product_id": null,
    "class_photo": "https:\/\/imgqn8.fruitday.com\/images\/2017-02-22\/4bf8f83f4cce396a43d3623142276a76.png",
    "send_region": null,
    "link": null,
    "is_split": "0",
    "is_hot": "0",
    "is_scene": "0",
    "banner_id": "0"
}, {
    "class2Id": "28",
    "id": "89",
    "name": "调味料",
    "parent_id": "28",
    "order_id": "1.00",
    "is_show": "1",
    "step": "3",
    "cat_path": "16,28",
    "ename": "",
    "photo": "https:\/\/imgqn9.fruitday.com\/",
    "product_id": null,
    "class_photo": "https:\/\/imgqn9.fruitday.com\/images\/2017-02-22\/990b36fd5c57b1b554e7a96f24184c7f.png",
    "send_region": null,
    "link": null,
    "is_split": "0",
    "is_hot": "0",
    "is_scene": "0",
    "banner_id": "0"
}, {
    "class2Id": "28",
    "id": "201",
    "name": "五谷杂粮",
    "parent_id": "28",
    "order_id": "0.00",
    "is_show": "1",
    "step": "3",
    "cat_path": "16,28",
    "ename": "",
    "photo": "https:\/\/imgjd4.fruitday.com\/",
    "product_id": null,
    "class_photo": "https:\/\/imgjd4.fruitday.com\/images\/2017-03-09\/0577e2356d1dedbfef905e1fe97e53e6.jpg",
    "send_region": null,
    "link": null,
    "is_split": "0",
    "is_hot": "0",
    "is_scene": "0",
    "banner_id": "0"
}, {
    "class2Id": "28",
    "id": "203",
    "name": "预混粉\/用途粉",
    "parent_id": "28",
    "order_id": "0.00",
    "is_show": "1",
    "step": "3",
    "cat_path": "16,28",
    "ename": "",
    "photo": "https:\/\/imgjd6.fruitday.com\/",
    "product_id": null,
    "class_photo": "https:\/\/imgjd6.fruitday.com\/images\/2017-03-09\/93c8174fbea8e407dc6a39807e26f7b1.jpg",
    "send_region": null,
    "link": null,
    "is_split": "0",
    "is_hot": "0",
    "is_scene": "0",
    "banner_id": "0"
}, {
    "class2Id": "28",
    "id": "202",
    "name": "泡菜罐头",
    "parent_id": "28",
    "order_id": "0.00",
    "is_show": "1",
    "step": "3",
    "cat_path": "16,28",
    "ename": "",
    "photo": "https:\/\/imgjd5.fruitday.com\/",
    "product_id": null,
    "class_photo": "https:\/\/imgjd5.fruitday.com\/images\/2017-03-11\/35a9061879b6f74c21bcc8b3398e545f.jpg",
    "send_region": null,
    "link": null,
    "is_split": "0",
    "is_hot": "0",
    "is_scene": "0",
    "banner_id": "0"
}]