[{
        "class2Id": "310",
        "id": "319",
        "name": "奇异果",
        "parent_id": "310",
        "order_id": "200.00",
        "is_show": "1",
        "step": "3",
        "cat_path": "303,310",
        "ename": "",
        "photo": "https:\/\/imgjd5.fruitday.com\/",
        "product_id": null,
        "class_photo": "https:\/\/imgjd5.fruitday.com\/images\/2017-09-19\/2e7463ed7ab392af0fd3370586cad765.png",
        "send_region": null,
        "link": null,
        "is_split": "0",
        "is_hot": "0",
        "is_scene": "0",
        "banner_id": "0"
      }, {
        "class2Id": "310",
        "id": "320",
        "name": "苹果",
        "parent_id": "310",
        "order_id": "195.00",
        "is_show": "1",
        "step": "3",
        "cat_path": "303,310",
        "ename": "",
        "photo": "https:\/\/imgjd6.fruitday.com\/",
        "product_id": null,
        "class_photo": "https:\/\/imgjd6.fruitday.com\/images\/2017-09-19\/315492971f93b7c3be196e3a7607dfae.png",
        "send_region": null,
        "link": null,
        "is_split": "0",
        "is_hot": "0",
        "is_scene": "0",
        "banner_id": "0"
      }, {
        "class2Id": "310",
        "id": "321",
        "name": "橙柑橘柚",
        "parent_id": "310",
        "order_id": "190.00",
        "is_show": "1",
        "step": "3",
        "cat_path": "303,310",
        "ename": "",
        "photo": "https:\/\/imgjd7.fruitday.com\/",
        "product_id": null,
        "class_photo": "https:\/\/imgjd7.fruitday.com\/images\/2017-09-19\/c24ec3729633a5a5ede075ebcb12fb7b.png",
        "send_region": null,
        "link": null,
        "is_split": "0",
        "is_hot": "0",
        "is_scene": "0",
        "banner_id": "0"
      }, {
        "class2Id": "310",
        "id": "322",
        "name": "蓝莓\/莓类",
        "parent_id": "310",
        "order_id": "185.00",
        "is_show": "1",
        "step": "3",
        "cat_path": "303,310",
        "ename": "",
        "photo": "https:\/\/imgqn8.fruitday.com\/",
        "product_id": null,
        "class_photo": "https:\/\/imgqn8.fruitday.com\/images\/2018-01-10\/de617cf9998865337ab754e930874615.jpg",
        "send_region": null,
        "link": null,
        "is_split": "0",
        "is_hot": "0",
        "is_scene": "0",
        "banner_id": "0"
      }, {
        "class2Id": "310",
        "id": "323",
        "name": "牛油果",
        "parent_id": "310",
        "order_id": "185.00",
        "is_show": "1",
        "step": "3",
        "cat_path": "303,310",
        "ename": "",
        "photo": "https:\/\/imgqn9.fruitday.com\/",
        "product_id": null,
        "class_photo": "https:\/\/imgqn9.fruitday.com\/images\/2017-09-19\/19926bcc7ea89d625b544939942d228e.png",
        "send_region": null,
        "link": null,
        "is_split": "0",
        "is_hot": "0",
        "is_scene": "0",
        "banner_id": "0"
      }, {
        "class2Id": "310",
        "id": "324",
        "name": "冷冻虾类",
        "parent_id": "310",
        "order_id": "180.00",
        "is_show": "1",
        "step": "3",
        "cat_path": "303,310",
        "ename": "",
        "photo": "https:\/\/imgjd1.fruitday.com\/",
        "product_id": null,
        "class_photo": "https:\/\/imgjd1.fruitday.com\/images\/2017-09-19\/c244ee074affb7df9596265b85f7f522.png",
        "send_region": null,
        "link": null,
        "is_split": "0",
        "is_hot": "0",
        "is_scene": "0",
        "banner_id": "0"
      }, {
        "class2Id": "310",
        "id": "327",
        "name": "牛排",
        "parent_id": "310",
        "order_id": "180.00",
        "is_show": "1",
        "step": "3",
        "cat_path": "303,310",
        "ename": "",
        "photo": "https:\/\/imgjd4.fruitday.com\/",
        "product_id": null,
        "class_photo": "https:\/\/imgjd4.fruitday.com\/images\/2017-09-19\/150cac7bb274ff768f58e10ce8838de7.png",
        "send_region": null,
        "link": null,
        "is_split": "0",
        "is_hot": "0",
        "is_scene": "0",
        "banner_id": "0"
      }, {
        "class2Id": "310",
        "id": "326",
        "name": "牛肉类",
        "parent_id": "310",
        "order_id": "165.00",
        "is_show": "1",
        "step": "3",
        "cat_path": "303,310",
        "ename": "",
        "photo": "https:\/\/imgjd3.fruitday.com\/",
        "product_id": null,
        "class_photo": "https:\/\/imgjd3.fruitday.com\/images\/2017-09-19\/f9910592199add9c473eb005163b0014.png",
        "send_region": null,
        "link": null,
        "is_split": "0",
        "is_hot": "0",
        "is_scene": "0",
        "banner_id": "0"
      }, {
        "class2Id": "310",
        "id": "367",
        "name": "冰鲜鱼类",
        "parent_id": "310",
        "order_id": "162.00",
        "is_show": "1",
        "step": "3",
        "cat_path": "303,310",
        "ename": "",
        "photo": "https:\/\/imgqn8.fruitday.com\/",
        "product_id": null,
        "class_photo": "https:\/\/imgqn8.fruitday.com\/images\/2018-01-10\/14775dade98d8d783b5a19b12230ed71.png",
        "send_region": null,
        "link": null,
        "is_split": "0",
        "is_hot": "0",
        "is_scene": "0",
        "banner_id": "0"
      }, {
        "class2Id": "310",
        "id": "329",
        "name": "冷藏酸奶",
        "parent_id": "310",
        "order_id": "155.00",
        "is_show": "1",
        "step": "3",
        "cat_path": "303,310",
        "ename": "",
        "photo": "https:\/\/imgjd6.fruitday.com\/",
        "product_id": null,
        "class_photo": "https:\/\/imgjd6.fruitday.com\/images\/2017-09-19\/3f231620aeb8c67c7221315808976a17.png",
        "send_region": null,
        "link": null,
        "is_split": "0",
        "is_hot": "0",
        "is_scene": "0",
        "banner_id": "0"
      }, {
        "class2Id": "310",
        "id": "330",
        "name": "根茎类",
        "parent_id": "310",
        "order_id": "150.00",
        "is_show": "1",
        "step": "3",
        "cat_path": "303,310",
        "ename": "",
        "photo": "https:\/\/imgjd7.fruitday.com\/",
        "product_id": null,
        "class_photo": "https:\/\/imgjd7.fruitday.com\/images\/2017-09-19\/d754853f15db126bee0dd8169deb9515.png",
        "send_region": null,
        "link": null,
        "is_split": "0",
        "is_hot": "0",
        "is_scene": "0",
        "banner_id": "0"
      }, {
        "class2Id": "310",
        "id": "332",
        "name": "蛋类",
        "parent_id": "310",
        "order_id": "140.00",
        "is_show": "1",
        "step": "3",
        "cat_path": "303,310",
        "ename": "",
        "photo": "https:\/\/imgqn9.fruitday.com\/",
        "product_id": null,
        "class_photo": "https:\/\/imgqn9.fruitday.com\/images\/2017-09-19\/1d48e8c8d91b9fc8923441c798c7b8e1.png",
        "send_region": null,
        "link": null,
        "is_split": "0",
        "is_hot": "0",
        "is_scene": "0",
        "banner_id": "0"
      }]